lmhtools/__init__.py
lmhtools/name/__init__.py
lmhtools/name/data.py
lmhtools/name/pyname.py
lmhtools/trans/__init__.py
lmhtools/trans/google.py
lmhtools-0.0.2.dist-info/LICENSE
lmhtools-0.0.2.dist-info/METADATA
lmhtools-0.0.2.dist-info/WHEEL
lmhtools-0.0.2.dist-info/top_level.txt
lmhtools-0.0.2.dist-info/RECORD
