Metadata-Version: 2.1
Name: lmhtools
Version: 0.0.2
Summary: lmhtools
Home-page: https://github.com/mengnan254/lmhtools
Author: lmh
Author-email: 297279618@qq.com
License: MIT Licence
Keywords: pip,lmh,lmhtools,liumenghua
Platform: any
Requires-Dist: PyExecJS
Requires-Dist: requests
Requires-Dist: numpy
